MANIFEST.in
README.md
setup.py
./fast_bleu/__init__.py
./fast_bleu/__python_wrapper__.py
./fast_bleu/__test__.py
./fast_bleu/cpp_sources/headers/bleu.h
./fast_bleu/cpp_sources/headers/bleu_revbleu.h
./fast_bleu/cpp_sources/headers/counter.h
./fast_bleu/cpp_sources/headers/custmap.h
./fast_bleu/cpp_sources/headers/fraction.h
./fast_bleu/cpp_sources/headers/nltk.h
./fast_bleu/cpp_sources/headers/self_bleu.h
./fast_bleu/cpp_sources/sources/bleu.cpp
./fast_bleu/cpp_sources/sources/bleu_revbleu.cpp
./fast_bleu/cpp_sources/sources/counter.cpp
./fast_bleu/cpp_sources/sources/custmap.cpp
./fast_bleu/cpp_sources/sources/fastbleu_module.cpp
./fast_bleu/cpp_sources/sources/fraction.cpp
./fast_bleu/cpp_sources/sources/nltk.cpp
./fast_bleu/cpp_sources/sources/self_bleu.cpp
fast_bleu/__init__.py
fast_bleu/__python_wrapper__.py
fast_bleu/__test__.py
fast_bleu.egg-info/PKG-INFO
fast_bleu.egg-info/SOURCES.txt
fast_bleu.egg-info/dependency_links.txt
fast_bleu.egg-info/top_level.txt
fast_bleu/cpp_sources/sources/bleu.cpp
fast_bleu/cpp_sources/sources/bleu_revbleu.cpp
fast_bleu/cpp_sources/sources/counter.cpp
fast_bleu/cpp_sources/sources/custmap.cpp
fast_bleu/cpp_sources/sources/fastbleu_module.cpp
fast_bleu/cpp_sources/sources/fraction.cpp
fast_bleu/cpp_sources/sources/nltk.cpp
fast_bleu/cpp_sources/sources/self_bleu.cpp