Metadata-Version: 2.1
Name: fast-bleu
Version: 0.0.89
Summary: A fast multithreaded C++ implementation of nltk BLEU with python wrapper.
Home-page: https://github.com/Danial-Alh/fast-bleu
Author: Danial Alihosseini
Author-email: danial.alihosseini@gmail.com
License: OSI Approved :: MIT License
Platform: POSIX :: Linux
Platform: MacOS
Classifier: Programming Language :: Python :: 3
Classifier: License :: OSI Approved :: MIT License
Classifier: Operating System :: POSIX :: Linux
Classifier: Operating System :: MacOS
Classifier: Development Status :: 3 - Alpha
Obsoletes: FastBLEU
Requires-Python: >=3.3
